{
   "type": "entity",
   "mixins": "stonehearth:mixins:item_properties",
   "components": {
      "model_variants": {
         "mixintypes": {
            "rabbit_male": "override",
            "rabbit_female": "override"
         },
         "rabbit_male": {
            "layer": "clothing",
            "models": [
               "file(amberstone_winter_worker_outfit.qb)",
               "file(amberstone_winter_worker_outfit_hood.qb)"
            ]
         },
         "rabbit_female": {
            "layer": "clothing",
            "models": [
               "file(amberstone_winter_worker_outfit_female.qb)",
               "file(amberstone_winter_worker_outfit_hood_female.qb)"
            ]
         }
      }
   }
}
